{
  "products": [
    {
      "name": "Bread Boy",
      "price": 15,
      "bps": 0.5,
      "eps": 0,
      "cps": 0,
      "pps": 0
    },
    {
      "name": "Alchemical Kitchen",
      "price": 100,
      "bps": 3,
      "eps": 0,
      "cps": 0,
      "pps": 0,
      "prereqs": {
        "productCount": {
          "product": "Bread Boy",
          "count": 1
        }
      }
    },
    {
      "name": "House Elves",
      "price": 1000,
      "bps": 10,
      "eps": 0.5,
      "cps": 0,
      "pps": 0,
      "prereqs": {
        "rank": 1
      }
    },
    {
      "name": "Marble Slab",
      "price": 5000,
      "bps": 100,
      "eps": 3,
      "cps": 0,
      "pps": 0,
      "prereqs": {
        "rank": 1,
        "eclairs": 15
      }
    },
    {
      "name": "Cupcake Wand",
      "price": 50000,
      "bps": 300,
      "eps": 0,
      "cps": 0.5,
      "pps": 0,
      "prereqs": {
        "rank": 2
      }
    },
    {
      "name": "Spirit Gate",
      "price": 70000,
      "bps": 4000,
      "eps": 0,
      "cps": 2,
      "pps": 0,
      "prereqs": {
        "rank": 2,
        "cupcakes": 10
      }
    },
    {
      "name": "Fruit Pie Trees",
      "price": 110000,
      "bps": 1500,
      "eps": 0,
      "cps": 0,
      "pps": 0.5,
      "prereqs": {
        "rank": 3
      }
    },
    {
      "name": "Oven",
      "price": 150000,
      "bps": 3000,
      "eps": 0,
      "cps": 0,
      "pps": 1.5,
      "prereqs": {
        "rank": 3,
        "pies": 5
      }
    }
  ]
}
